bizydraft/__init__.py
bizydraft/block_nodes.py
bizydraft/env.py
bizydraft/hijack_nodes.py
bizydraft/hijack_routes.py
bizydraft/oss_utils.py
bizydraft/patch_handlers.py
bizydraft/postload.py
bizydraft/prestartup_patch.py
bizydraft/resp.py
bizydraft/server.py
bizydraft/workflow_io.py
bizydraft/static/js/aiAppHandler.js
bizydraft/static/js/clipspaceToOss.js
bizydraft/static/js/disableComfyWebSocket.js
bizydraft/static/js/freezeModeHandler.js
bizydraft/static/js/handleStyle.js
bizydraft/static/js/hookLoadMedia.js
bizydraft/static/js/hookLoadModel.js
bizydraft/static/js/main.js
bizydraft/static/js/nodeFocusHandler.js
bizydraft/static/js/nodeParamsFilter.js
bizydraft/static/js/postEvent.js
bizydraft/static/js/socket.js
bizydraft/static/js/tool.js
bizydraft/static/js/uploadFile.js
bizydraft/static/js/workflow_io.js
bizydraft/static/js/hookLoad/configLoader.js
bizydraft/static/js/hookLoad/media.js
bizydraft/static/js/hookLoad/model.js
bizydraft-0.2.86.dist-info/METADATA
bizydraft-0.2.86.dist-info/WHEEL
bizydraft-0.2.86.dist-info/top_level.txt
bizydraft-0.2.86.dist-info/RECORD
