Metadata-Version: 2.4
Name: bizydraft
Version: 0.2.86
Summary: bizydraft
Requires-Dist: loguru
Requires-Dist: aiohttp
Requires-Dist: werkzeug
Requires-Dist: oss2
